tfdiagrams/__init__.py
tfdiagrams/console/__init__.py
tfdiagrams/generate.py
tfdiagrams/resources/blank.png
tfdiagrams/resources.py
tfdiagrams-0.5.0.dist-info/METADATA
tfdiagrams-0.5.0.dist-info/WHEEL
tfdiagrams-0.5.0.dist-info/entry_points.txt
tfdiagrams-0.5.0.dist-info/licenses/LICENSE
tfdiagrams-0.5.0.dist-info/RECORD
