Metadata-Version: 2.4
Name: tfdiagrams
Version: 0.5.0
Summary: 
License-File: LICENSE
Author: Tetsuya Shinone
Author-email: info@semnil.com
Requires-Python: >=3.12,<4.0
Classifier: Programming Language :: Python :: 3
Classifier: Programming Language :: Python :: 3.12
Classifier: Programming Language :: Python :: 3.13
Classifier: Programming Language :: Python :: 3.14
Requires-Dist: diagrams (>=0.25.1,<0.26.0)
Requires-Dist: pydot (>=4.0.1,<5.0.0)
